<?xml version="1.0" encoding="utf-8" ?>
<Defs>
	<TraitDef>
		<defName>Ark_Outspoken</defName>
		<commonality>0.7</commonality>
		<degreeDatas>
			<li>
				<label>直言不讳</label>
				<description>{PAWN_nameDef}说话十分坦率，毫无顾忌，并且很难被改变想法，但{PAWN_pronoun}也会为改善这种状况积极地学习。</description>
				<marketValueFactorOffset>-0.20</marketValueFactorOffset>
				<statOffsets>
					<GlobalLearningFactor>0.30</GlobalLearningFactor>
					<NegotiationAbility>-0.30</NegotiationAbility>
				</statOffsets>
				<statFactors>
					<CertaintyLossFactor MayRequire="Ludeon.RimWorld.Ideology">0.5</CertaintyLossFactor>
				</statFactors>
			</li>
		</degreeDatas>
		<requiredWorkTags>
			<li>Social</li>
		</requiredWorkTags>
	</TraitDef>

	<TraitDef>
		<defName>Ark_Trait_Nature</defName>
		<commonality>1</commonality>
		<degreeDatas>
			<li>
				<label>生于自然</label>
				<description>{PAWN_nameDef}能很好地适应在自然环境中的生活，但{PAWN_pronoun}非常不擅长与精密器械打交道并排斥植入假体，也许只是需要一点时间适应？。</description>
				<skillGains>
					<li>
						<key>Construction</key>
						<value>4</value>
					</li>
					<li>
						<key>Plants</key>
						<value>4</value>
					</li>
					<li>
						<key>Intellectual</key>
						<value>-4</value>
					</li>
				</skillGains>
				<statOffsets>
					<PlantHarvestYield>0.1</PlantHarvestYield>
					<PlantWorkSpeed>0.1</PlantWorkSpeed>
				</statOffsets>
				<statFactors>
					<MechRepairSpeed>0.1</MechRepairSpeed>
					<FixBrokenDownBuildingSuccessChance>0.2</FixBrokenDownBuildingSuccessChance>
				</statFactors>
			</li>
		</degreeDatas>
		<requiredWorkTags>
			<li>PlantWork</li>
		</requiredWorkTags>
		<conflictingTraits>
			<li>BodyPurist</li>
			<li>Transhumanist</li>
		</conflictingTraits>
	</TraitDef>

	<TraitDef>
		<defName>Ark_Trait_Aggressor</defName>
		<commonality>0.7</commonality>
		<degreeDatas>
			<li>
				<label>挑衅者</label>
				<description>{PAWN_nameDef}不屑于躲避敌人的攻击与隐藏自己并且痴迷在战场上横冲直撞收割生命的感觉，因此{PAWN_pronoun}成了医务室的常客。</description>
				<statOffsets>
					<MeleeDodgeChance>-10</MeleeDodgeChance>
					<HuntingStealth>-0.25</HuntingStealth>
				</statOffsets>
			</li>
		</degreeDatas>
		<requiredWorkTags>
			<li>Violent</li>
		</requiredWorkTags>
	</TraitDef>
	
	<TraitDef>
		<defName>Ark_Trait_Careless</defName>
		<commonality>1.2</commonality>
		<degreeDatas>
			<li>
				<label>神经大条</label>
				<description>{PAWN_nameDef}性格率直且不擅思考，工作也很粗心，虽然经常被骗但{PAWN_pronoun}对待别人温和友善。</description>
				<socialFightChanceFactor>0</socialFightChanceFactor>
				<statFactors>
					<WorkSpeedGlobal>1.2</WorkSpeedGlobal>
					<ConstructSuccessChance>0.5</ConstructSuccessChance>
					<FixBrokenDownBuildingSuccessChance>0.5</FixBrokenDownBuildingSuccessChance>
				</statFactors>
				<statOffsets>
					<TradePriceImprovement>-0.5</TradePriceImprovement>
				</statOffsets>
			</li>
		</degreeDatas>
		<conflictingTraits>
			<li>Cannibal</li>
			<li>Psychopath</li>
		</conflictingTraits>
	</TraitDef>
</Defs>